{ "_id" : { "$oid" : "53ac097155de671f34de5167" }, "guid" : "0DE5307528A1B81F776E95F92E4E712C", "name" : "Funny29", "names" : [ "Funny29" ], "online" : false, "score" : null, "team" : null }
{ "_id" : { "$oid" : "53ac097155de671f34de5168" }, "bot" : false, "guid" : "1BC36FEB7B208A9E3D51667B2C0D2AE1", "headmodel" : "tony", "name" : "Action^1Henk", "names" : [ "Action^1Henk" ], "online" : false, "score" : null, "skill" : null, "team" : null, "team_id" : 0 }
{ "_id" : { "$oid" : "53ac097155de671f34de5169" }, "bot" : false, "guid" : "1EAB6C49095DA5F4AB9ECD5B4365696F", "headmodel" : "tony", "name" : "[HOPS] freestalker", "names" : [ "freestalker", "[HOPS] freestalker" ], "online" : false, "score" : 0, "skill" : null, "team" : "", "team_id" : 0 }
{ "_id" : { "$oid" : "53ac4e7f55de674d72f50b29" }, "bot" : false, "guid" : "9982DEAC44F27E0622FCF0FC6C540F45", "headmodel" : "tony", "name" : "^3Bunny^2Drops", "names" : [ "UnnamedPlayer", "-[aequitas]-", "[SOEN] aequitas", "^4Action^5Hops", "Action^1Honk", "Action^1Hunk", "^3Bunny^2Drops" ], "online" : false, "score" : null, "skill" : null, "team" : null, "team_id" : 0 }
{ "_id" : { "$oid" : "53ad49ae55de6747aae1c340" }, "guid" : "6AE50857ABFC67960BAC283234404AE6", "name" : "[HOPS] Feldwebel", "names" : [ "Feldwebel", "[HOPS] Feldwebel" ], "online" : false, "score" : null, "team" : null }
{ "_id" : { "$oid" : "53ad49ae55de6747aae1c341" }, "guid" : "34B38922F3E5BDF19BA7E9032C6A9BA4", "name" : "Funny29", "names" : [ "Grummaway", "Funny29" ], "online" : false, "score" : null, "team" : null }
{ "_id" : { "$oid" : "53ad49af55de6747aae1c342" }, "bot" : false, "guid" : "8B0870E9DB02BFE9172E7C096E58F49D", "headmodel" : "sarge", "name" : "^5[HOPS]^1Brensen^7", "names" : [ "^8Henkiepenkie^7", "UnnamedPlayer", "^5[HOPS]^1Brensen^7" ], "online" : false, "score" : null, "skill" : null, "team" : null, "team_id" : 0 }
{ "_id" : { "$oid" : "53ad4a3555de6747bf1b6ba2" }, "guid" : "310306C2F31EA4788AD80E2F695BA408", "name" : "^5Snoop ^6Dog", "names" : [ "^5Te^6rr^5or", "^5Snoop ^6Dog" ], "online" : false, "score" : null, "team" : null }
{ "_id" : { "$oid" : "53ad4ac655de6748a7f699d7" }, "bot" : false, "guid" : "9CD101D150811D227AB7EF2C65082083", "headmodel" : "sarge", "name" : "^3Bunny^2Hops", "names" : [ "^6In^2Terminator", "^1[^0soen^1]^6In^2Terminator", "^1[^2SOEN^1]^6In^2Terminator", "^3In^2Terminator", "^3Bunny^2Hops" ], "online" : false, "score" : null, "skill" : null, "team" : null, "team_id" : 1 }
{ "_id" : { "$oid" : "53ad4ae855de6748a7f699d8" }, "bot" : false, "guid" : "ED2E68A00AF6C2392919BCD0F029D0BD", "headmodel" : "assassin", "name" : "^1Rem^3co", "names" : [ "^4Mother^6Henk", "^8Remco^6nator", "^1[^3Remco^1]", "^1[^3SOEN^1]YOLOMOFO", "^1Wiener^2Kopf", "^1Rem^3co" ], "online" : false, "score" : null, "skill" : null, "team" : null }
{ "_id" : { "$oid" : "53ad4bae55de6748a7f699de" }, "guid" : "6B90AE0FA56F5A162858CD149BAE6DA1", "name" : "!!!!!!!!", "names" : [ "!!!!!!!!" ], "online" : false, "score" : null, "team" : null }
{ "_id" : { "$oid" : "53ad66bb55de676b20af8d57" }, "guid" : "", "names" : [] }
{ "_id" : { "$oid" : "53ad81d755de671592713fe9" }, "guid" : "007F50573E960D82C1D3658603035484", "name" : "feldschwein", "names" : [ "feldschwein" ], "online" : false, "score" : null, "team" : null }
{ "_id" : { "$oid" : "53ad870c55de671592714003" }, "bot" : false, "guid" : "C7542A672F4542A230E8EBE276EA1D48", "headmodel" : "liz", "name" : "^2Bunny^5Socks", "names" : [ "^2Henkie Spankie", "[HOpschen] 2^Henkie", "[HOpschen] ^2Henkie", "Bunny Socks", "^2BUnny^5Socks", "^2Bunny^5Socks" ], "online" : false, "score" : null, "skill" : null, "team" : null, "team_id" : 0 }
{ "_created" : { "$date" : 1403963076000 }, "_id" : { "$oid" : "53aec6c455de6759084b5ffe" }, "_updated" : { "$date" : 1403963076000 }, "bot" : false, "guid" : "4149407351D856EBE4C59B969BAA68B2", "name" : "-[aequitas]-", "names" : [ "test", "test name", "^1t^2a", "-[aequitas]-" ], "online" : false, "score" : null, "skill" : null, "team" : null }
{ "_created" : { "$date" : 1403990325000 }, "_id" : { "$oid" : "53af313555de6705d026ea55" }, "_updated" : { "$date" : 1403990325000 }, "bot" : true, "guid" : "1", "name" : "Murielle", "names" : [ "Skelebot", "Sorceress", "Arachna", "Grunt", "Murielle" ], "online" : false, "score" : null, "skill" : "4.00", "team" : null }
{ "_created" : { "$date" : 1403990435000 }, "_id" : { "$oid" : "53af31a355de6705d026ea56" }, "_updated" : { "$date" : 1403990435000 }, "bot" : true, "guid" : "2", "name" : "Tanisha", "names" : [ "Angelyss", "Morgan", "Ayumi", "Tanisha" ], "online" : false, "score" : null, "skill" : "4.00", "team" : null }
{ "_created" : { "$date" : 1403990776000 }, "_id" : { "$oid" : "53af32f855de6705d026ea58" }, "_updated" : { "$date" : 1403990776000 }, "bot" : true, "guid" : "0", "name" : "Murielle", "names" : [ "Broadklin", "Beret", "S_Marine", "Angelyss", "Murielle" ], "online" : false, "score" : null, "skill" : "4.00", "team" : null }
{ "_created" : { "$date" : 1403991802000 }, "_id" : { "$oid" : "53af36fa55de6711634788af" }, "_updated" : { "$date" : 1403991802000 }, "bot" : false, "guid" : "None", "headmodel" : "tony", "name" : "-[aequitas]-", "names" : [ "Broadklin", "Angelyss", "Sorceress", "Sergei", "Beret", "Morgan", "Metalbot", "S_Marine", "Ayumi", "Liz", "Grunt", "-[aequitas]-", "Murielle", "Tanisha", "Action^1Henk", "^1Rem^3co", "^3Bunny^2Hops", "[HOPS] freestalker", "^5[HOPS]^1Brensen^7" ], "online" : false, "score" : null, "skill" : null, "team" : null, "team_id" : null }
{ "_created" : { "$date" : 1403992971000 }, "_id" : { "$oid" : "53af3b8b55de67150cf88b15" }, "_updated" : { "$date" : 1403992971000 }, "bot" : true, "guid" : "3", "name" : "Liz", "names" : [ "Sergei", "S_Marine", "Liz" ], "online" : false, "score" : null, "skill" : "4.00", "team" : null }
{ "_created" : { "$date" : 1404127273000 }, "_id" : { "$oid" : "53b1482955de6764336b103d" }, "_updated" : { "$date" : 1404127273000 }, "bot" : false, "guid" : "58FCB03CA362EBB2BE4A53BDAAF0E0D3", "headmodel" : "sarge", "name" : "[HOPS] Feldwebel", "names" : [ "UnnamedPlayer", "[HOPS] Feldwebel" ], "online" : false, "score" : null, "skill" : null, "team" : null, "team_id" : 0 }
{ "_created" : { "$date" : 1404297275000 }, "_id" : { "$oid" : "53b3e03b55de671b1374fa46" }, "_updated" : { "$date" : 1404297275000 }, "bot" : false, "guid" : "079A1CB8385B17209DB73B0DAE6C9BF3", "headmodel" : "beret", "name" : "ActionHank", "names" : [ "Ricardo", "ActionSpank", "ActionHank" ], "online" : false, "score" : null, "skill" : null, "team" : null, "team_id" : 1 }
{ "_created" : { "$date" : 1404298553000 }, "_id" : { "$oid" : "53b3e53955de671b1374fa5b" }, "_updated" : { "$date" : 1404298553000 }, "bot" : false, "guid" : "0A47F9BC8AC297302F6DD7CC24B8B678", "headmodel" : "sarge", "name" : "Dyson", "names" : [ "Intern-al Error", "Dyson" ], "online" : false, "score" : null, "skill" : null, "team" : null, "team_id" : 0 }
{ "_created" : { "$date" : 1404378932000 }, "_id" : { "$oid" : "53b51f3455de670449a084b9" }, "_updated" : { "$date" : 1404378932000 }, "bot" : false, "guid" : "A294EC500C15A04B5710E57AC6640C56", "headmodel" : "skelebot", "name" : "Funny29", "names" : [ "F29", "Funny29", "^1I^2Want^3A^5Good^6Gun^8To" ], "online" : false, "score" : null, "skill" : null, "team" : null, "team_id" : 3 }
